setup.py
isup/__init__.py
isup/cli.py
isup.egg-info/PKG-INFO
isup.egg-info/SOURCES.txt
isup.egg-info/dependency_links.txt
isup.egg-info/entry_points.txt
isup.egg-info/requires.txt
isup.egg-info/top_level.txt
tests/__init__.py
tests/test_cli.py